pydbinterface/__init__.py
pydbinterface/main.py
pydbinterface-0.0.1.dist-info/licenses/LICENSE
pydbinterface-0.0.1.dist-info/METADATA
pydbinterface-0.0.1.dist-info/WHEEL
pydbinterface-0.0.1.dist-info/top_level.txt
pydbinterface-0.0.1.dist-info/RECORD
