Metadata-Version: 2.4
Name: pydbinterface
Version: 0.0.1
Summary: Interfaz sencilla para conectar y manipular bases de datos en Python
Author: darth wayne
Author-email: darrthwayne@gmail.com
License: MIT
Requires-Python: >=3.6
License-File: LICENSE
Dynamic: author
Dynamic: author-email
Dynamic: description
Dynamic: description-content-type
Dynamic: license
Dynamic: license-file
Dynamic: requires-python
Dynamic: summary
